README.rst
flask_idempotent.py
setup.cfg
setup.py
Flask_Idempotent.egg-info/PKG-INFO
Flask_Idempotent.egg-info/SOURCES.txt
Flask_Idempotent.egg-info/dependency_links.txt
Flask_Idempotent.egg-info/not-zip-safe
Flask_Idempotent.egg-info/requires.txt
Flask_Idempotent.egg-info/top_level.txt