Metadata-Version: 1.1
Name: Flask-Idempotent
Version: 0.1.0
Summary: Idempotent requests for Flask applications
Home-page: http://github.com/DisruptiveLabs/flask-idempotent
Author: Franklyn Tackitt
Author-email: frank@comanage.com
License: MIT
Platform: any
Classifier: Environment :: Web Environment
Classifier: Intended Audience :: Developers
Classifier: License :: OSI Approved :: MIT License
Classifier: Operating System :: OS Independent
Classifier: Programming Language :: Python
Classifier: Topic :: Internet :: WWW/HTTP :: Dynamic Content
Classifier: Topic :: Software Development :: Libraries :: Python Modules
